{
  "title": "NewProject_1",
  "packageName": "org.cocos2d.demo",
  "startScene": "15cf4ca0-08c5-47b4-876b-9e62abb2c0eb",
  "excludeScenes": [],
  "orientation": {
    "landscapeRight": true,
    "landscapeLeft": true,
    "portrait": false,
    "upsideDown": false
  },
  "webOrientation": "auto",
  "inlineSpriteFrames": true,
  "inlineSpriteFrames_native": true,
  "mainCompressionType": "merge_all_json",
  "mainIsRemote": false,
  "optimizeHotUpdate": false,
  "md5Cache": true,
  "nativeMd5Cache": true,
  "encryptJs": true,
  "xxteaKey": "c78c2f16-037e-46",
  "zipCompressJs": true,
  "fb-instant-games": {},
  "android": {
    "packageName": "org.cocos2d.demo",
    "REMOTE_SERVER_ROOT": ""
  },
  "ios": {
    "packageName": "org.cocos2d.demo",
    "REMOTE_SERVER_ROOT": "",
    "ios_enable_jit": true
  },
  "mac": {
    "packageName": "org.cocos2d.demo",
    "REMOTE_SERVER_ROOT": "",
    "width": 1280,
    "height": 720
  },
  "win32": {
    "REMOTE_SERVER_ROOT": "",
    "width": 1280,
    "height": 720
  },
  "android-instant": {
    "packageName": "org.cocos2d.demo",
    "REMOTE_SERVER_ROOT": "",
    "pathPattern": "",
    "scheme": "https",
    "host": "",
    "skipRecord": false,
    "recordPath": ""
  },
  "appBundle": false,
  "agreements": {}
}
